Metadata-Version: 1.0
Name: image-filter-tjr
Version: 0.0.0
Summary: Simple and Auto Thresholding of Images
Home-page: UNKNOWN
Author: UNKNOWN
Author-email: UNKNOWN
License: UNKNOWN
Platform: UNKNOWN
